pinai_intent_sdk/__init__.py
pinai_intent_sdk/exceptions.py
pinai_intent_sdk/models.py
pinai_intent_sdk/pinai_intent_sdk.py
pinai_intent_sdk-0.1.2.dist-info/LICENSE
pinai_intent_sdk-0.1.2.dist-info/METADATA
pinai_intent_sdk-0.1.2.dist-info/WHEEL
pinai_intent_sdk-0.1.2.dist-info/top_level.txt
pinai_intent_sdk-0.1.2.dist-info/RECORD
