Metadata-Version: 2.1
Name: pinai-intent-sdk
Version: 0.1.2
Summary: SDK for PINAI Intent Match API
Home-page: https://pinai.io
Author: smile
Author-email: smile@pinai.io
Project-URL: Bug Tracker, https://github.com/yourusername/pinai-intent-sdk/issues
Project-URL: Documentation, https://docs.pinai.io
Project-URL: Source Code, https://github.com/yourusername/pinai-intent-sdk
Keywords: pinai,intent,sdk,api,machine learning,ai
Classifier: Development Status :: 3 - Alpha
Classifier: Intended Audience :: Developers
Classifier: Topic :: Software Development :: Libraries :: Python Modules
Classifier: Programming Language :: Python :: 3
Classifier: Programming Language :: Python :: 3.10
Classifier: Programming Language :: Python :: 3.11
Classifier: License :: OSI Approved :: MIT License
Classifier: Operating System :: OS Independent
Requires-Python: >=3.10
License-File: LICENSE
Requires-Dist: fastapi>=0.68.0
Requires-Dist: uvicorn>=0.15.0
Requires-Dist: pydantic>=1.8.0
Requires-Dist: requests>=2.26.0
Requires-Dist: python-dotenv>=0.19.0
